flymeyun_fos/__init__.py
flymeyun_fos/compat.py
flymeyun_fos/exception.py
flymeyun_fos/fos_base_client.py
flymeyun_fos/fos_client_configuration.py
flymeyun_fos/fos_response.py
flymeyun_fos/protocol.py
flymeyun_fos/region.py
flymeyun_fos/utils.py
flymeyun_fos/auth/__init__.py
flymeyun_fos/auth/fos_credentials.py
flymeyun_fos/auth/fos_signer.py
flymeyun_fos/http/__init__.py
flymeyun_fos/http/fos_http_client.py
flymeyun_fos/http/handler.py
flymeyun_fos/http/http_content_types.py
flymeyun_fos/http/http_headers.py
flymeyun_fos/http/http_methods.py
flymeyun_fos/retry/__init__.py
flymeyun_fos/retry/retry_policy.py
flymeyun_fos/services/__init__.py
flymeyun_fos/services/fos/__init__.py
flymeyun_fos/services/fos/canned_acl.py
flymeyun_fos/services/fos/fos_client.py
flymeyun_fos/services/fos/fos_handler.py
flymeyun_fos/services/fos/storage_class.py
flymeyun_fos-0.9.11.dist-info/LICENSE
flymeyun_fos-0.9.11.dist-info/METADATA
flymeyun_fos-0.9.11.dist-info/WHEEL
flymeyun_fos-0.9.11.dist-info/top_level.txt
flymeyun_fos-0.9.11.dist-info/RECORD
