Metadata-Version: 2.1
Name: flymeyun-fos
Version: 0.9.11
Summary: Flymeyun FOS SDK for python
Home-page: https://www.flymeyun.com/#/product/fos/index
Author: 
Author-email: 
License: Apache License 2.0
Platform: UNKNOWN
Requires-Python: >=2.7, !=3.0.*, !=3.1.*, !=3.2.*, <4
Requires-Dist: pycryptodome (>=3.8.0)
Requires-Dist: future (>=0.6.0)
Requires-Dist: six (>=1.4.0)
